{"cameraMode":{"drawMode":0,"name":"Shaded","section":"Shading Mode"},"sceneLighting":true,"audioPlay":false,"sceneViewState":{"m_AlwaysRefresh":false,"showFog":true,"showSkybox":true,"showFlares":true,"showImageEffects":true,"showParticleSystems":true,"showVisualEffectGraphs":true,"m_FxEnabled":true},"in2DMode":false,"pivot":{"x":0.21777915954589845,"y":0.7308101654052734,"z":483.75},"rotation":{"x":0.038721345365047458,"y":-0.11931439489126206,"z":0.004652710165828466,"w":0.9920953512191773},"size":610.0452270507813,"orthographic":true}